Metadata-Version: 2.1
Name: vdu-nlp-services
Version: 0.0.19
Summary: Python wrapper for VDU NLP online services
Home-page: https://github.com/aleksas/vdu-nlp-services
Author: Aleksas Pielikis
Author-email: ant.kampo@gmail.com
License: UNKNOWN
Platform: UNKNOWN
Classifier: Programming Language :: Python :: 3
Classifier: License :: OSI Approved :: MIT License
Classifier: Operating System :: OS Independent
Requires-Python: >=2.7
